jaccs/__init__.py
jaccs/jaccs.py
jaccs/version.py
jaccs-1.0.0.dist-info/DESCRIPTION.rst
jaccs-1.0.0.dist-info/METADATA
jaccs-1.0.0.dist-info/RECORD
jaccs-1.0.0.dist-info/WHEEL
jaccs-1.0.0.dist-info/metadata.json
jaccs-1.0.0.dist-info/top_level.txt
