Metadata-Version: 2.0
Name: jaccs
Version: 1.0.0
Summary: Write strings to access nested JSON objects
Home-page: https://github.com/jiffyclub/jaccs
Author: Matt Davis
Author-email: jiffyclub@gmail.com
License: UNKNOWN
Platform: UNKNOWN
Classifier: License :: OSI Approved :: BSD License
Classifier: Operating System :: OS Independent
Classifier: Programming Language :: Python
Classifier: Programming Language :: Python :: 2.7
Classifier: Programming Language :: Python :: 3
Classifier: Programming Language :: Python :: 3.3
Classifier: Programming Language :: Python :: 3.4
Classifier: Programming Language :: Python :: 3.5
